home/__init__.py
home/admin.py
home/all_function.py
home/apps.py
home/forecasting_function.py
home/forms.py
home/llm_models.py
home/models.py
home/prompts.py
home/tests.py
home/tools.py
home/urls.py
home/views.py
home/migrations/__init__.py
portfolio_ai/__init__.py
portfolio_ai/installer.py
portfolio_ai/setup.sh
portfolio_site/__init__.py
portfolio_site/asgi.py
portfolio_site/settings.py
portfolio_site/urls.py
portfolio_site/wsgi.py
rag_app/__init__.py
rag_app/admin.py
rag_app/apps.py
rag_app/models.py
rag_app/tests.py
rag_app/urls.py
rag_app/vfaissdb.py
rag_app/views.py
rag_app/migrations/__init__.py
sentiment_analysis/__init__.py
sentiment_analysis/admin.py
sentiment_analysis/apps.py
sentiment_analysis/forms.py
sentiment_analysis/lstm_model.py
sentiment_analysis/models.py
sentiment_analysis/tests.py
sentiment_analysis/urls.py
sentiment_analysis/views.py
sentiment_analysis/migrations/__init__.py
webscrape_qa/__init__.py
webscrape_qa/admin.py
webscrape_qa/apps.py
webscrape_qa/forms.py
webscrape_qa/models.py
webscrape_qa/prompt_scrap.py
webscrape_qa/tests.py
webscrape_qa/urls.py
webscrape_qa/views.py
webscrape_qa/migrations/__init__.py
portfolio_ai-0.1.2.dist-info/METADATA
portfolio_ai-0.1.2.dist-info/WHEEL
portfolio_ai-0.1.2.dist-info/entry_points.txt
portfolio_ai-0.1.2.dist-info/top_level.txt
portfolio_ai-0.1.2.dist-info/RECORD
