Metadata-Version: 2.1
Name: portfolio-ai
Version: 0.1.2
Summary: AI-powered portfolio project setup script
Home-page: https://github.com/in2itsaurabh/portfolio_ai
Author: saurabh tiwari
Author-email: saurabhin2it@gmail.com
License: UNKNOWN
Platform: UNKNOWN
Classifier: Programming Language :: Python :: 3
Classifier: License :: OSI Approved :: MIT License
Requires-Dist: gitpython
